webpilot/__init__.py
webpilot/config.py
webpilot/models.py
webpilot/robot.py
webpilot-0.3.0.dist-info/LICENSE
webpilot-0.3.0.dist-info/METADATA
webpilot-0.3.0.dist-info/WHEEL
webpilot-0.3.0.dist-info/top_level.txt
webpilot-0.3.0.dist-info/RECORD
